<monster name="Lilith" nameDescription="Lilith" race="VENOM" experience="350000" speed="1000" manacost="0">
        <health now="100000" max="100000"/>
        <look type="12" head="16" body="64" legs="52" feet="52" corpse="5527" addons="3"/>
        <targetchange interval="2000" chance="50"/>
        <strategy attack="90" defense="10"/>
<flags>
        <flag summonable="0"/>
        <flag attackable="1"/>
        <flag hostile="1"/>
        <flag illusionable="1"/>
        <flag convinceable="0"/>
        <flag pushable="0"/>
        <flag canpushitems="1"/>
        <flag canpushcreatures="1"/>
        <flag targetdistance="1"/>
        <flag runonhealth="0"/>
        <flag skull="4"/>
</flags>
<attacks>
<attack name="melee" interval="2000" min="-700" max="-1050"/>
<attack name="poison" interval="1000" chance="17" range="7" target="1" min="-600" max="-1000">
<attribute key="shootEffect" value="poison"/>
<attribute key="areaEffect" value="greenspark"/>
</attack>
<attack name="earth" interval="3000" chance="20" length="8" spread="3" min="-900" max="-1200">
<attribute key="areaEffect" value="poison"/>
</attack>
<attack name="lifedrain" interval="1000" chance="15" length="8" spread="0" min="-700" max="-2800">
<attribute key="areaEffect" value="redshimmer"/>
</attack>
<attack name="physical" interval="1000" chance="40" radius="8" target="0" min="-700" max="-2300">
<attribute key="areaEffect" value="holyarea"/>
</attack>
</attacks>

<defenses armor="20" defense="20">
        <defense name="healing" interval="1000" chance="5" min="800" max="1400">
        <attribute key="areaEffect" value="redshimmer"/>
        </defense>
        <defense name="healing" interval="1000" chance="1" min="400" max="1000">
        <attribute key="areaEffect" value="redshimmer"/>
        </defense>
        <defense name="speed" interval="1000" chance="1" speedchange="2500" duration="1000000">
        <attribute key="areaEffect" value="blueshimmer"/>
        </defense>
</defenses>

<immunities>
        <immunity physical="0"/>
        <immunity energy="0"/>
        <immunity fire="0"/>
        <immunity poison="1"/>
        <immunity lifedrain="0"/>
        <immunity paralyze="1"/>
        <immunity outfit="0"/>
        <immunity drunk="1"/>
        <immunity invisible="1"/>
</immunities>
        <voices interval="2000" chance="40">
        <voice sentence="TASTE MY VENOM!"/>
        <voice sentence="I don't think I like you anymore.."/>
        <voice sentence="I CAN SMELL YOUR BLOOD!"/>
        <voice sentence="LILITH WILL MURDER ALL WHO STANDS A THREAT!"/>
        <voice sentence="I AM LILITH!"/>
        <voice sentence="Good luck trying to kill me! HAAHAHAHA"/>
</voices>

<loot capacity="5000">
        <item id="2142" countmax="1" chance="350000"/>
        <item id="2158" countmax="1" chance="150000"/>
        <item id="2195" countmax="1" chance="400000"/>
        <item id="2124" countmax="1" chance="550000"/>
        <item id="2520" countmax="1" chance="1550000"/>
        <item id="2393" countmax="1" chance="120500"/>
        <item id="2179" countmax="1" chance="800000"/>
        <item id="2470" countmax="1" chance="500000"/>
        <item id="2493" countmax="1" chance="150000"/>
        <item id="2494" countmax="1" chance="150000"/>
        <item id="2495" countmax="1" chance="150000"/>
        <item id="5741" countmax="1" chance="150000"/>

</loot>

</monster>
